tangled_agent/__init__.py
tangled_agent/__main__.py
tangled_agent/base_agent.py
tangled_agent/base_game_player.py
tangled_agent/basic_game.py
tangled_agent/config_handler.py
tangled_agent/connection/__init__.py
tangled_agent/connection/api_connection.py
tangled_agent/connection/auth0_handler.py
tangled_agent/get_builtin_agents.py
tangled_agent/graph_display.py
tangled_agent/local_game_player.py
tangled_agent/main.py
tangled_agent/pretty_game.py
tangled_agent/random_agent.py
tangled_agent/remote_game_player.py
tangled_agent/sample_agent.py
tangled_agent-1.3.1.dist-info/METADATA
tangled_agent-1.3.1.dist-info/WHEEL
tangled_agent-1.3.1.dist-info/RECORD
