Metadata-Version: 2.1
Name: tangled-agent
Version: 1.3.1
Summary: A package for tangled-agent
Author: erik
Author-email: erik@snowdropquantum.com
Requires-Python: >=3.8,<4.0
Classifier: Programming Language :: Python :: 3
Classifier: Programming Language :: Python :: 3.8
Classifier: Programming Language :: Python :: 3.9
Classifier: Programming Language :: Python :: 3.10
Classifier: Programming Language :: Python :: 3.11
Classifier: Programming Language :: Python :: 3.12
Classifier: Programming Language :: Python :: 3.13
Requires-Dist: PyJWT (>=2.8.0)
Requires-Dist: configargparse (>=1.7)
Requires-Dist: requests (>=2.25.1)
Requires-Dist: tangled-game-client (==4.0.0)
Requires-Dist: tangled-game-engine (==2.2.0)
